by/__init__.py
by-0.0.7.dist-info/licenses/LICENSE
by-0.0.7.dist-info/METADATA
by-0.0.7.dist-info/WHEEL
by-0.0.7.dist-info/top_level.txt
by-0.0.7.dist-info/RECORD
