Metadata-Version: 2.4
Name: by
Version: 0.0.7
Summary: selection tools
Home-page: https://github.com/t-c-w/by
Author: Thor Whalen
License: mit
Keywords: matching,pairs,intervals,selection,nearest neighbors
Platform: any
License-File: LICENSE
Requires-Dist: numpy
Requires-Dist: scikit-learn
Dynamic: license-file
